advanced_analytics/features/_init_.py
advanced_analytics/features/features.py
advanced_analytics/model/_init_.py
advanced_analytics/model/model.py
advanced_analytics/preprocessing/__init__.py
advanced_analytics/preprocessing/preprocessing.py
advanced_analytics_coke-0.1.2.dist-info/METADATA
advanced_analytics_coke-0.1.2.dist-info/WHEEL
advanced_analytics_coke-0.1.2.dist-info/top_level.txt
advanced_analytics_coke-0.1.2.dist-info/RECORD
