Metadata-Version: 2.1
Name: advanced-analytics-coke
Version: 0.1.2
Summary: library
Home-page: UNKNOWN
Author: AA Team
Author-email: 
License: Open_Source
Platform: UNKNOWN
Classifier: Intended Audience :: Developers
Classifier: License :: Free For Educational Use
Classifier: Programming Language :: Python
Classifier: Programming Language :: Python :: 3
Classifier: Programming Language :: Python :: 3.6
Classifier: Programming Language :: Python :: 3.7
Classifier: Programming Language :: Python :: 3.8
Classifier: Programming Language :: Python :: 3.9
Classifier: Operating System :: OS Independent
Requires-Dist: numpy
